LAB1/DecadeCntr/VCD4RE.v
module VCD4RE ( input clk, output wire TC,
                input ce, output wire CEO,
                input r,
                output reg [3:0] Q=0 );
assign TC = (Q==9) ;
assign CEO = ce & TC ;
always @ (posedge clk) begin
Q <= (r | CEO)? 0 : ce? Q+1 : Q ;
end
endmodule

LAB1/DecadeCntr/top.v
`timescale 1 ns / 100 ps

module top();

reg clk = 1'b0;

always begin
   #1 clk = ~clk;
end

reg ce = 1'b1;
wire [3:0]Q;
wire TC;
wire CEO;
reg r = 1'b0;

VCD4RE DecadeCntr(.clk(clk), .TC(TC), .ce(ce), .CEO(CEO), .r(r), .Q(Q));

initial begin
    $dumpvars;
    $display("Starting simulation");
    #32 $finish;

end

endmodule

LAB1/DecadeCntr/dump.vcd
$date
	Fri Feb 10 17:57:30 2023
$end
$version
	Icarus Verilog
$end
$timescale
	100ps
$end
$scope module top $end
$var wire 1 ! TC $end
$var wire 4 " Q [3:0] $end
$var wire 1 # CEO $end
$var reg 1 $ ce $end
$var reg 1 % clk $end
$var reg 1 & r $end
$scope module DecadeCntr $end
$var wire 1 # CEO $end
$var wire 1 $ ce $end
$var wire 1 % clk $end
$var wire 1 & r $end
$var wire 1 ! TC $end
$var reg 4 ' Q [3:0] $end
$upscope $end
$upscope $end
$enddefinitions $end
#0
$dumpvars
b0 '
0&
0%
1$
0#
b0 "
0!
$end
#10
b1 "
b1 '
1%
#20
0%
#30
b10 "
b10 '
1%
#40
0%
#50
b11 "
b11 '
1%
#60
0%
#70
b100 "
b100 '
1%
#80
0%
#90
b101 "
b101 '
1%
#100
0%
#110
b110 "
b110 '
1%
#120
0%
#130
b111 "
b111 '
1%
#140
0%
#150
b1000 "
b1000 '
1%
#160
0%
#170
1#
1!
b1001 "
b1001 '
1%
#180
0%
#190
0#
0!
b0 "
b0 '
1%
#200
0%
#210
b1 "
b1 '
1%
#220
0%
#230
b10 "
b10 '
1%
#240
0%
#250
b11 "
b11 '
1%
#260
0%
#270
b100 "
b100 '
1%
#280
0%
#290
b101 "
b101 '
1%
#300
0%
#310
b110 "
b110 '
1%
