LAB1/BinarySumCntr/VCB4RE.v
`define m 4
`timescale 1 ns / 100 ps

module VCBmCE( input ce, output reg [3:0]Q = 0,
                input clk, output wire TC,
                input s, output wire CEO);
assign TC = (Q == ((1 << `m) - 1));
assign CEO = ce & TC;
always @(posedge clk or posedge s) begin
  Q <= s ? 0 : ce ? Q + 1 : Q;
end
endmodule

LAB1/BinarySumCntr/top.v
`timescale 1 ns / 100 ps

module top();

reg clk = 1'b0;

always begin
   #1 clk = ~clk;
end

reg ce = 1'b1;
wire [3:0]Q;
wire TC;
wire CEO;
reg s = 1'b0;

VCBmCE SubCntr(.ce(ce), .Q(Q), .clk(clk), .TC(TC), .s(s), .CEO(CEO));

initial begin
    $dumpvars;
    $display("Starting simulation");
    #32 $finish;

end

endmodule

LAB1/BinarySumCntr/dump.vcd
$date
	Thu Mar  2 01:46:25 2023
$end
$version
	Icarus Verilog
$end
$timescale
	100ps
$end
$scope module top $end
$var wire 1 ! TC $end
$var wire 4 " Q [3:0] $end
$var wire 1 # CEO $end
$var reg 1 $ ce $end
$var reg 1 % clk $end
$var reg 1 & s $end
$scope module SubCntr $end
$var wire 1 # CEO $end
$var wire 1 $ ce $end
$var wire 1 % clk $end
$var wire 1 & s $end
$var wire 1 ! TC $end
$var reg 4 ' Q [3:0] $end
$upscope $end
$upscope $end
$enddefinitions $end
#0
$dumpvars
b0 '
0&
0%
1$
0#
b0 "
0!
$end
#10
b1 "
b1 '
1%
#20
0%
#30
b10 "
b10 '
1%
#40
0%
#50
b11 "
b11 '
1%
#60
0%
#70
b100 "
b100 '
1%
#80
0%
#90
b101 "
b101 '
1%
#100
0%
#110
b110 "
b110 '
1%
#120
0%
#130
b111 "
b111 '
1%
#140
0%
#150
b1000 "
b1000 '
1%
#160
0%
#170
b1001 "
b1001 '
1%
#180
0%
#190
b1010 "
b1010 '
1%
#200
0%
#210
b1011 "
b1011 '
1%
#220
0%
#230
b1100 "
b1100 '
1%
#240
0%
#250
b1101 "
b1101 '
1%
#260
0%
#270
b1110 "
b1110 '
1%
#280
0%
#290
1#
1!
b1111 "
b1111 '
1%
#300
0%
#310
0#
0!
b0 "
b0 '
1%
